LICENSE.txt
MANIFEST.in
README.md
ez_setup.py
requirements.txt
requirements_docs.txt
requirements_tests.txt
setup.py
crayola/__init__.py
crayola/crayola.py
crayola/tests.py
crayola.egg-info/PKG-INFO
crayola.egg-info/SOURCES.txt
crayola.egg-info/dependency_links.txt
crayola.egg-info/requires.txt
crayola.egg-info/top_level.txt
crayola.egg-info/zip-safe