Metadata-Version: 1.0
Name: crayola
Version: 0.1.1
Summary: A colored Python logging handler.
Home-page: http://github.com/tylerbutler/crayola
Author: Tyler Butler
Author-email: tyler@tylerbutler.com
License: MIT
Platform: any
